hay/__init__.py
hay/puppet.py
hay-0.0.7.dist-info/LICENSE.txt
hay-0.0.7.dist-info/METADATA
hay-0.0.7.dist-info/WHEEL
hay-0.0.7.dist-info/top_level.txt
hay-0.0.7.dist-info/RECORD
